MANIFEST.in
README.rst
setup.cfg
setup.py
source/RPIO/_RPIO.py
source/RPIO/__init__.py
source/RPIO.egg-info/PKG-INFO
source/RPIO.egg-info/SOURCES.txt
source/RPIO.egg-info/dependency_links.txt
source/RPIO.egg-info/top_level.txt
source/RPIO/PWM/__init__.py
source/c_gpio/Makefile
source/c_gpio/c_gpio.c
source/c_gpio/c_gpio.h
source/c_gpio/cpuinfo.c
source/c_gpio/cpuinfo.h
source/c_gpio/py_gpio.c
source/c_pwm/Makefile
source/c_pwm/pwm.c
source/c_pwm/pwm.h
source/c_pwm/pwm_py.c
source/c_pwm/servod.c
source/scripts/rpio
source/scripts/rpio-curses