Metadata-Version: 1.1
Name: RPIO
Version: 0.9.6
Summary: Advanced GPIO for the Raspberry Pi. Extends RPi.GPIO with PWM, GPIO interrups, TCP socket interrupts, command line tools and more
Home-page: https://github.com/metachris/RPIO
Author: Chris Hager
Author-email: chris@linuxuser.at
License: MIT
Keywords: raspberry,raspberry pi,interrupts,gpio,rpio
Platform: UNKNOWN
Classifier: Development Status :: 4 - Beta
Classifier: Programming Language :: Python
Classifier: Programming Language :: Python :: 3
Classifier: Operating System :: POSIX :: Linux
Classifier: Topic :: Utilities
Classifier: Topic :: Software Development
Classifier: Topic :: Home Automation
Classifier: Topic :: System :: Hardware
Classifier: Intended Audience :: Developers
Classifier: License :: OSI Approved :: GNU Lesser General Public License v3 or later (LGPLv3+)
Classifier: License :: Other/Proprietary License
